formulaic/__init__.py
formulaic/_version.py
formulaic/errors.py
formulaic/formula.py
formulaic/model_matrix.py
formulaic/model_spec.py
formulaic/sugar.py
formulaic/materializers/__init__.py
formulaic/materializers/arrow.py
formulaic/materializers/base.py
formulaic/materializers/pandas.py
formulaic/materializers/types/__init__.py
formulaic/materializers/types/enums.py
formulaic/materializers/types/evaluated_factor.py
formulaic/materializers/types/factor_values.py
formulaic/materializers/types/scoped_factor.py
formulaic/materializers/types/scoped_term.py
formulaic/parser/__init__.py
formulaic/parser/parser.py
formulaic/parser/utils.py
formulaic/parser/algos/__init__.py
formulaic/parser/algos/sanitize_tokens.py
formulaic/parser/algos/tokenize.py
formulaic/parser/algos/tokens_to_ast.py
formulaic/parser/types/__init__.py
formulaic/parser/types/ast_node.py
formulaic/parser/types/factor.py
formulaic/parser/types/formula_parser.py
formulaic/parser/types/operator.py
formulaic/parser/types/operator_resolver.py
formulaic/parser/types/ordered_set.py
formulaic/parser/types/term.py
formulaic/parser/types/token.py
formulaic/transforms/__init__.py
formulaic/transforms/basis_spline.py
formulaic/transforms/contrasts.py
formulaic/transforms/cubic_spline.py
formulaic/transforms/hashed.py
formulaic/transforms/identity.py
formulaic/transforms/lag.py
formulaic/transforms/patsy_compat.py
formulaic/transforms/poly.py
formulaic/transforms/scale.py
formulaic/utils/__init__.py
formulaic/utils/calculus.py
formulaic/utils/cast.py
formulaic/utils/code.py
formulaic/utils/constraints.py
formulaic/utils/context.py
formulaic/utils/deprecations.py
formulaic/utils/iterators.py
formulaic/utils/layered_mapping.py
formulaic/utils/null_handling.py
formulaic/utils/sentinels.py
formulaic/utils/sparse.py
formulaic/utils/stateful_transforms.py
formulaic/utils/structured.py
formulaic/utils/variables.py
formulaic-1.1.0.dist-info/METADATA
formulaic-1.1.0.dist-info/WHEEL
formulaic-1.1.0.dist-info/licenses/LICENSE
formulaic-1.1.0.dist-info/RECORD
