Metadata-Version: 2.4
Name: formulaic
Version: 1.1.0
Summary: An implementation of Wilkinson formulas.
Project-URL: repository, https://github.com/matthewwardrop/formulaic
Project-URL: documentation, https://matthewwardrop.github.io/formulaic
Author-email: Matthew Wardrop <mpwardrop@gmail.com>
License-Expression: MIT
License-File: LICENSE
Classifier: Development Status :: 5 - Production/Stable
Classifier: Environment :: Console
Classifier: Intended Audience :: Developers
Classifier: Intended Audience :: Information Technology
Classifier: Intended Audience :: Science/Research
Classifier: License :: OSI Approved :: MIT License
Classifier: Natural Language :: English
Classifier: Operating System :: OS Independent
Classifier: Programming Language :: Python :: 3.7
Classifier: Programming Language :: Python :: 3.8
Classifier: Programming Language :: Python :: 3.9
Classifier: Programming Language :: Python :: 3.10
Classifier: Programming Language :: Python :: 3.11
Classifier: Programming Language :: Python :: 3.12
Classifier: Programming Language :: Python :: 3.13
Classifier: Topic :: Scientific/Engineering :: Mathematics
Requires-Python: >=3.7.2
Requires-Dist: astor>=0.8; python_version < '3.9'
Requires-Dist: cached-property>=1.3.0; python_version < '3.8'
Requires-Dist: graphlib-backport>=1.0.0; python_version < '3.9'
Requires-Dist: interface-meta>=1.2.0
Requires-Dist: numpy>=1.16.5
Requires-Dist: pandas>=1.0
Requires-Dist: scipy>=1.6
Requires-Dist: typing-extensions>=4.2.0
Requires-Dist: wrapt>=1.0; python_version < '3.13'
Requires-Dist: wrapt>=1.17.0rc1; python_version >= '3.13'
Provides-Extra: arrow
Requires-Dist: pyarrow>=1; extra == 'arrow'
Provides-Extra: calculus
Requires-Dist: sympy!=1.10,>=1.3; extra == 'calculus'
